{
  "$schema": "./custom_train_config.schema.json",
  "episodes": 30000,
  "max_steps_per_episode": 3000,
  "gamma": 0.99,
  "learning_rate": 0.0001,
  "weight_decay": 1e-05,
  "batch_size": 128,
  "replay_capacity": 50000,
  "min_replay_size": 3000,
  "train_frequency": 4,
  "target_update_interval": 2000,
  "grad_clip_norm": 5.0,
  "epsilon_start": 1.0,
  "epsilon_end": 0.03,
  "epsilon_decay_steps": 200000,
  "eval_episodes": 20,
  "moving_avg_window": 100,
  "log_interval": 10,
  "checkpoint_interval": 500,
  "tensorboard_log_interval": 5,
  "jsonl_flush_interval": 20,
  "run_name": "custom",
  "output_root": "runs",
  "live_plot": false,
  "tensorboard": true,
  "save_csv": true,
  "save_jsonl": true,
  "device": "auto",
  "lightweight_step_info": true,
  "model_type": "adaptive_cnn",
  "local_patch_size": 11,
  "curriculum": null,
  "random_board": null,
  "parallel": {
    "enabled": false,
    "num_workers": 4,
    "queue_capacity": 8192,
    "weight_sync_interval_steps": 512,
    "actor_loop_sleep_ms": 0,
    "actor_seed_stride": 100000,
    "actor_device": "cpu"
  },
  "reward_weights": {
    "alive": -0.01,
    "food": 1.0,
    "bonusFood": 1.5,
    "death": -1.5,
    "timeout": -1.0,
    "levelUp": 0.2,
    "victory": 5.0,
    "foodDistanceK": 0.4
  },
  "env": {
    "difficulty": "normal",
    "mode": "classic",
    "board_size": 14,
    "enable_bonus_food": false,
    "enable_obstacles": false,
    "allow_leveling": false,
    "max_steps_without_food": 196,
    "seed": 42
  }
}